serializable_excel/__init__.py
serializable_excel/color_extractor.py
serializable_excel/colors.py
serializable_excel/descriptors.py
serializable_excel/excel_io.py
serializable_excel/excel_reader.py
serializable_excel/excel_types.py
serializable_excel/excel_writer.py
serializable_excel/exceptions.py
serializable_excel/field_extractor.py
serializable_excel/field_metadata.py
serializable_excel/models.py
serializable_excel/validators.py
serializable_excel-0.1.6.dist-info/licenses/LICENSE
serializable_excel-0.1.6.dist-info/METADATA
serializable_excel-0.1.6.dist-info/WHEEL
serializable_excel-0.1.6.dist-info/top_level.txt
serializable_excel-0.1.6.dist-info/RECORD
