Metadata-Version: 2.4
Name: serializable-excel
Version: 0.1.6
Summary: A user-friendly Python library for seamless bidirectional conversion between Excel spreadsheets and Pydantic models
Author: Dmitry Zaitsev
Maintainer: Dmitry Zaitsev
License: MIT License
Project-URL: Homepage, https://github.com/of1nn/serializable-excel
Project-URL: Documentation, https://of1nn.github.io/serializable-excel
Project-URL: Repository, https://github.com/of1nn/serializable-excel
Project-URL: Issues, https://github.com/of1nn/serializable-excel/issues
Keywords: excel,pydantic,serialization,data-validation,spreadsheet
Classifier: Development Status :: 3 - Alpha
Classifier: Intended Audience :: Developers
Classifier: Programming Language :: Python :: 3
Classifier: Programming Language :: Python :: 3.8
Classifier: Programming Language :: Python :: 3.9
Classifier: Programming Language :: Python :: 3.10
Classifier: Programming Language :: Python :: 3.11
Classifier: Programming Language :: Python :: 3.12
Classifier: Topic :: Software Development :: Libraries :: Python Modules
Classifier: Topic :: Office/Business :: Financial :: Spreadsheet
Requires-Python: >=3.8
License-File: LICENSE
Requires-Dist: pydantic<3.0.0,>=2.0.0
Requires-Dist: openpyxl>=3.0.0
Provides-Extra: dev
Requires-Dist: pytest>=7.0.0; extra == "dev"
Requires-Dist: pytest-cov>=4.0.0; extra == "dev"
Requires-Dist: black>=23.0.0; extra == "dev"
Requires-Dist: ruff>=0.1.0; extra == "dev"
Dynamic: license-file
